AcdemyAI.py
AcdemyAI-1.0.1.dist-info/METADATA
AcdemyAI-1.0.1.dist-info/WHEEL
AcdemyAI-1.0.1.dist-info/top_level.txt
AcdemyAI-1.0.1.dist-info/RECORD
